LiveObjects/Connection.py
LiveObjects/__init__.py
LiveObjects/credentials.py
LiveObjects/hal.py
LiveObjects/services.py
LiveObjects-2.1.0.dist-info/LICENSE.md
LiveObjects-2.1.0.dist-info/METADATA
LiveObjects-2.1.0.dist-info/WHEEL
LiveObjects-2.1.0.dist-info/top_level.txt
LiveObjects-2.1.0.dist-info/RECORD
