Metadata-Version: 2.1
Name: LiveObjects
Version: 2.1.0
Summary: This module allows to easy send data to Orange LiveObjects using Python3 and uPython
Home-page: https://github.com/DatavenueLiveObjects/LiveObjects_SDK_for_Python
Author: Kacper Sawicki, Krzysztof Krześlak, Tomasz Malek
License: MIT
Platform: UNKNOWN
Requires-Dist: paho-mqtt
